helper_i18n/__init__.py
helper_i18n/handler/docs_handler.py
helper_i18n/handler/exception_handler.py
helper_i18n/handler/i18n_handler.py
helper_i18n/typing.py
helper_i18n/utils.py
i18n_fastapi_helper-0.3.0.dist-info/METADATA
i18n_fastapi_helper-0.3.0.dist-info/WHEEL
i18n_fastapi_helper-0.3.0.dist-info/entry_points.txt
i18n_fastapi_helper-0.3.0.dist-info/RECORD
